drfwn_quick/__init__.py
drfwn_quick/data.py
drfwn_quick/serializers.py
drfwn_quick/settings.py
drfwn_quick/utils.py
drfwn_quick/viewsets.py
drfwn_quick-0.1.0.dist-info/LICENSE
drfwn_quick-0.1.0.dist-info/METADATA
drfwn_quick-0.1.0.dist-info/WHEEL
drfwn_quick-0.1.0.dist-info/RECORD
