Metadata-Version: 2.1
Name: drfwn-quick
Version: 0.1.0
Summary: 
License: MIT
Author: LamerLink
Author-email: 36551116+LamerLink@users.noreply.github.com
Requires-Python: >=3.9,<4.0
Classifier: License :: OSI Approved :: MIT License
Classifier: Programming Language :: Python :: 3
Classifier: Programming Language :: Python :: 3.9
Classifier: Programming Language :: Python :: 3.10
Classifier: Programming Language :: Python :: 3.11
Classifier: Programming Language :: Python :: 3.12
Requires-Dist: Django (>=4.1.7,<5.0.0)
Requires-Dist: djangorestframework (>=3.14.0,<4.0.0)
Requires-Dist: drf-writable-nested (>=0.7.0,<0.8.0)
